reviewtally/__init__.py
reviewtally/analysis/__init__.py
reviewtally/analysis/sprint_periods.py
reviewtally/analysis/team_metrics.py
reviewtally/cache/__init__.py
reviewtally/cache/cache_manager.py
reviewtally/cache/sqlite_cache.py
reviewtally/cli/__init__.py
reviewtally/cli/parse_cmd_line.py
reviewtally/data_collection.py
reviewtally/exceptions/__init__.py
reviewtally/exceptions/local_exceptions.py
reviewtally/exporters/__init__.py
reviewtally/exporters/sprint_export.py
reviewtally/main.py
reviewtally/metrics_calculation.py
reviewtally/output_formatting.py
reviewtally/queries/__init__.py
reviewtally/queries/get_prs.py
reviewtally/queries/get_repos_gql.py
reviewtally/queries/get_reviewers_rest.py
reviewtally/visualization/__init__.py
reviewtally/visualization/individual_plot.py
reviewtally/visualization/sprint_plot.py
review_tally-0.5.4.dist-info/METADATA
review_tally-0.5.4.dist-info/WHEEL
review_tally-0.5.4.dist-info/entry_points.txt
review_tally-0.5.4.dist-info/licenses/LICENSE
review_tally-0.5.4.dist-info/RECORD
