Metadata-Version: 2.4
Name: review-tally
Version: 0.5.4
Summary: A tool to discover who is reviewing your organization's PRs
License: Apache
License-File: LICENSE
Author: ghinks
Author-email: ghinks@yahoo.com
Requires-Python: >=3.11,<4.0
Classifier: License :: Other/Proprietary License
Classifier: Programming Language :: Python :: 3
Classifier: Programming Language :: Python :: 3.11
Classifier: Programming Language :: Python :: 3.12
Classifier: Programming Language :: Python :: 3.13
Classifier: Programming Language :: Python :: 3.14
Requires-Dist: aiohttp (>=3.11.2,<4.0.0)
Requires-Dist: aioresponses (>=0.7.7,<0.8.0)
Requires-Dist: asyncio (>=3.4.3,<5.0.0)
Requires-Dist: dash (>=3.2.0,<4.0.0)
Requires-Dist: mypy (>=1.14.1,<2.0.0)
Requires-Dist: plotly (>=6.3.0,<7.0.0)
Requires-Dist: requests (>=2.32.3,<3.0.0)
Requires-Dist: ruff (>=0.13.3,<0.15.0)
Requires-Dist: tabulate (>=0.9.0,<0.10.0)
Requires-Dist: tqdm (>=4.67.1,<5.0.0)
Requires-Dist: types-requests (>=2.32.0.20241016,<3.0.0.0)
Requires-Dist: types-tabulate (>=0.9.0.20241207,<0.10.0.0)
Requires-Dist: types-tqdm (>=4.67.0.20250301,<5.0.0.0)
Project-URL: Repository, https://github.com/ghinks/review-tally
